rmq_definitions.py
rmq_definitions-1.0.1.dist-info/DESCRIPTION.rst
rmq_definitions-1.0.1.dist-info/METADATA
rmq_definitions-1.0.1.dist-info/RECORD
rmq_definitions-1.0.1.dist-info/WHEEL
rmq_definitions-1.0.1.dist-info/entry_points.txt
rmq_definitions-1.0.1.dist-info/metadata.json
rmq_definitions-1.0.1.dist-info/top_level.txt
rmq_definitions-1.0.1.dist-info/zip-safe
